{
  "team_name": "Creators Studio Team",
  "team_description": "A composite team for writing, storytelling, and content production. It combines classical literary masters with modern creators for novels, scripts, brand copy, and multi-platform content.",
  "members": [
    {
      "name": "Li Bai",
      "description": "A Tang poet with powerful imagination and expressive language for creative ideation.",
      "soul_path": "/real_world/li_bai/",
      "download_url": "/real_world/li_bai/SOUL.en.md",
      "category": "real_world"
    },
    {
      "name": "Du Fu",
      "description": "Known for social depth and disciplined structure, ideal for thematic refinement.",
      "soul_path": "/real_world/du_fu/",
      "download_url": "/real_world/du_fu/SOUL.en.md",
      "category": "real_world"
    },
    {
      "name": "William Shakespeare",
      "description": "A master of drama and character arcs, excellent at conflict and dialogue.",
      "soul_path": "/real_world/william_shakespeare/",
      "download_url": "/real_world/william_shakespeare/SOUL.en.md",
      "category": "real_world"
    },
    {
      "name": "Cao Xueqin",
      "description": "A representative of long-form narrative and ensemble characterization.",
      "soul_path": "/real_world/cao_xueqin/",
      "download_url": "/real_world/cao_xueqin/SOUL.en.md",
      "category": "real_world"
    },
    {
      "name": "Editor",
      "description": "Refines structure, logic, and clarity to improve manuscript quality.",
      "soul_path": "/personas/editor/",
      "download_url": "/personas/editor/SOUL.en.md",
      "category": "personas"
    },
    {
      "name": "Fiction Coach",
      "description": "Focuses on plot, characters, and chapter progression for readable output.",
      "soul_path": "/personas/fiction_coach/",
      "download_url": "/personas/fiction_coach/SOUL.en.md",
      "category": "personas"
    },
    {
      "name": "Copywriting Master",
      "description": "Optimizes messaging for reach and conversion in marketing contexts.",
      "soul_path": "/personas/copywriting_master/",
      "download_url": "/personas/copywriting_master/SOUL.en.md",
      "category": "personas"
    },
    {
      "name": "Screenwriting Consultant",
      "description": "Specializes in scene rhythm and dramatic structure for production-ready scripts.",
      "soul_path": "/personas/screenwriting_consultant/",
      "download_url": "/personas/screenwriting_consultant/SOUL.en.md",
      "category": "personas"
    },
    {
      "name": "Poetry Mentor",
      "description": "Strengthens imagery, rhythm, and rhetorical quality in poetic writing.",
      "soul_path": "/personas/poetry_mentor/",
      "download_url": "/personas/poetry_mentor/SOUL.en.md",
      "category": "personas"
    }
  ],
  "tags": [
    "Creation",
    "Writing",
    "Storytelling",
    "Copywriting",
    "Content"
  ],
  "image": "https://robohash.org/agent-souls-creators-studio-team.png?size=1200x630&set=set4&bgset=bg1",
  "source": "https://agent-souls.com",
  "generated_at": "2026-03-19T00:25:12+00:00"
}